seven_shell_studio/__init__.py
seven_shell_studio/route.py
seven_shell_studio/handlers/__init__.py
seven_shell_studio/handlers/seven_base.py
seven_shell_studio/handlers/api/__init__.py
seven_shell_studio/handlers/api/integral.py
seven_shell_studio/models/__init__.py
seven_shell_studio/models/db_models/__init__.py
seven_shell_studio/models/db_models/exchange/__init__.py
seven_shell_studio/models/db_models/exchange/exchange_model.py
seven_shell_studio/models/db_models/exchange/exchange_model_ex.py
seven_shell_studio/models/db_models/goods/__init__.py
seven_shell_studio/models/db_models/goods/goods_model.py
seven_shell_studio/models/db_models/inventory/__init__.py
seven_shell_studio/models/db_models/inventory/inventory_record_model.py
seven_shell_studio-1.0.13.dist-info/LICENSE
seven_shell_studio-1.0.13.dist-info/METADATA
seven_shell_studio-1.0.13.dist-info/WHEEL
seven_shell_studio-1.0.13.dist-info/top_level.txt
seven_shell_studio-1.0.13.dist-info/RECORD
